cmdfinder/__init__.py
cmdfinder/history.py
cmdfinder/config/__init__.py
cmdfinder/config/config.py
cmdfinder/db/__init__.py
cmdfinder/db/db.py
cmdfinder/db/insert_command.py
cmdfinder/ui/__init__.py
cmdfinder/ui/app.py
cmdfinder/ui/app.tcss
cmdfinder/utils/__init__.py
cmdfinder/utils/logger.py
cmdfinder/utils/service_installer.py
cmdfinder/utils/shell_utils.py
cmdfinder/utils/watcher.py
cmdfinder-2.3.0.dist-info/licenses/LICENSE
cmdfinder-2.3.0.dist-info/METADATA
cmdfinder-2.3.0.dist-info/WHEEL
cmdfinder-2.3.0.dist-info/entry_points.txt
cmdfinder-2.3.0.dist-info/top_level.txt
cmdfinder-2.3.0.dist-info/RECORD
