Metadata-Version: 2.4
Name: cmdfinder
Version: 2.3.0
Summary: Search and run shell history with a Textual TUI
Requires-Python: >=3.10
License-File: LICENSE
Requires-Dist: linkify-it-py==2.0.3
Requires-Dist: markdown-it-py==4.0.0
Requires-Dist: mdit-py-plugins==0.5.0
Requires-Dist: mdurl==0.1.2
Requires-Dist: platformdirs==4.5.0
Requires-Dist: Pygments==2.19.2
Requires-Dist: RapidFuzz==3.14.3
Requires-Dist: rich==14.2.0
Requires-Dist: textual==6.6.0
Requires-Dist: typing_extensions==4.15.0
Requires-Dist: uc-micro-py==1.0.3
Requires-Dist: pygtail
Dynamic: description
Dynamic: description-content-type
Dynamic: license-file
Dynamic: requires-dist
Dynamic: requires-python
Dynamic: summary
